okutils/tools.cpython-37m-x86_64-linux-gnu.so
okutils/__init__.py
okutils/sdm/writer.py
okutils/sdm/decoders.py
okutils/sdm/reader.py
okutils/sdm/encoders.py
okutils/sdm/__init__.py
okutils/collections/groupby.py
okutils/collections/__init__.py
okutils/hash/jsonhash.py
okutils/hash/__init__.py
okutils/hash/hashbase.py
okutils-1.0.3.dist-info/WHEEL
okutils-1.0.3.dist-info/RECORD
okutils-1.0.3.dist-info/top_level.txt
okutils-1.0.3.dist-info/METADATA
