Metadata-Version: 2.2
Name: okutils
Version: 1.0.3
Summary: a python utils
Author-email: skiloop <skiloop@gmail.com>
License: MIT License
Project-URL: homepage, https://github.com/skiloop/okutils
Project-URL: repository, https://github.com/skiloop/okutils
Keywords: utils
Platform: x86_64
Platform: aarch64
Classifier: Operating System :: MacOS :: MacOS X
Classifier: Operating System :: POSIX :: Linux
Classifier: Operating System :: Microsoft :: Windows
Classifier: License :: OSI Approved :: MIT License
Classifier: Programming Language :: Python
Classifier: Programming Language :: Python :: 3
Classifier: Programming Language :: Python :: 3.7
Classifier: Programming Language :: Python :: 3.8
Classifier: Programming Language :: Python :: 3.9
Classifier: Topic :: Utilities
Classifier: Topic :: Software Development :: Libraries :: Python Modules
Requires-Python: >=3.7
